uzoncalc/__init__.py
uzoncalc/context.py
uzoncalc/context_options.py
uzoncalc/logger.py
uzoncalc/setup.py
uzoncalc/units.py
uzoncalc/handcalc/__init__.py
uzoncalc/handcalc/ast_instrument.py
uzoncalc/handcalc/ast_to_ir.py
uzoncalc/handcalc/ast_to_step.py
uzoncalc/handcalc/ast_validator.py
uzoncalc/handcalc/ast_visitor.py
uzoncalc/handcalc/exceptions.py
uzoncalc/handcalc/field_names.py
uzoncalc/handcalc/instrument_cache.py
uzoncalc/handcalc/ir.py
uzoncalc/handcalc/recorder.py
uzoncalc/handcalc/recording_injector.py
uzoncalc/handcalc/recording_state.py
uzoncalc/handcalc/steps.py
uzoncalc/handcalc/transformers.py
uzoncalc/handcalc/unit_collector.py
uzoncalc/handcalc/post_handlers/__init__.py
uzoncalc/handcalc/post_handlers/base_post_handler.py
uzoncalc/handcalc/post_handlers/parentheses_simplify.py
uzoncalc/handcalc/post_handlers/post_pipeline.py
uzoncalc/handcalc/post_handlers/subscriptify.py
uzoncalc/handcalc/post_handlers/swap_alias.py
uzoncalc/handcalc/post_handlers/swap_symbol.py
uzoncalc/template/__init__.py
uzoncalc/template/calc_template.html
uzoncalc/template/template.css
uzoncalc/template/utils.py
uzoncalc/tests/__init__.py
uzoncalc/tests/ast_print.py
uzoncalc/tests/example.py
uzoncalc/utils/__init__.py
uzoncalc/utils/doc.py
uzoncalc/utils/elements.py
uzoncalc/utils/options.py
uzoncalc/utils_extra/__init__.py
uzoncalc/utils_extra/excel.py
uzoncalc-1.0.1.dist-info/licenses/LICENSE
uzoncalc-1.0.1.dist-info/METADATA
uzoncalc-1.0.1.dist-info/WHEEL
uzoncalc-1.0.1.dist-info/top_level.txt
uzoncalc-1.0.1.dist-info/RECORD
