Metadata-Version: 2.4
Name: uzoncalc
Version: 1.0.1
Summary: UzonCalc is a tool for writing engineering calculation documents using Python. With it, you can write calculation reports as smoothly as writing Python, and benefit from the full Python ecosystem and AI assistance.
Home-page: https://github.com/uyoufu/UzonCalc
Author: uyoufu
Author-email: uyoufu@uzoncloud.com
Requires-Python: >=3.9
License-File: LICENSE
Requires-Dist: pint
Requires-Dist: numpy
Dynamic: author
Dynamic: author-email
Dynamic: description
Dynamic: description-content-type
Dynamic: home-page
Dynamic: license-file
Dynamic: requires-dist
Dynamic: requires-python
Dynamic: summary
